ks_metric/__init__.py
ks_metric/_ks_metric.py
ks_metric-0.2.0.dist-info/LICENSE
ks_metric-0.2.0.dist-info/METADATA
ks_metric-0.2.0.dist-info/WHEEL
ks_metric-0.2.0.dist-info/top_level.txt
ks_metric-0.2.0.dist-info/RECORD
