Metadata-Version: 2.1
Name: ks-metric
Version: 0.2.0
Summary: Kolmogorov-Smirnov metric for machine learning
Home-page: https://github.com/nottherealsanta/ks_metric
Author: nottherealsanta
Author-email: santosh.rajan.work@gmail.com
License: MIT license
Keywords: ks_metric
Platform: UNKNOWN
Classifier: Development Status :: 2 - Pre-Alpha
Classifier: Intended Audience :: Developers
Classifier: License :: OSI Approved :: MIT License
Classifier: Natural Language :: English
Classifier: Programming Language :: Python :: 3
Classifier: Programming Language :: Python :: 3.6
Classifier: Programming Language :: Python :: 3.7
Classifier: Programming Language :: Python :: 3.8
Requires-Python: >=3.6
License-File: LICENSE
